fireeyepy/__init__.py
fireeyepy/errors.py
fireeyepy-1.3.0.dist-info/METADATA
fireeyepy-1.3.0.dist-info/WHEEL
fireeyepy-1.3.0.dist-info/top_level.txt
fireeyepy-1.3.0.dist-info/RECORD
