Metadata-Version: 2.1
Name: fireeyepy
Version: 1.3.0
Summary: FireEye Client Library for Python
Home-page: https://github.com/fireeye/fireeye-python
Author: FireEye
Author-email: developers@fireeye.com
License: MIT
Platform: any
Requires-Python: >=3.6
Requires-Dist: requests (>=2.4.2)
